AUTHORS.rst
CONTRIBUTING.rst
HISTORY.rst
LICENSE
MANIFEST.in
README.rst
setup.cfg
setup.py
docs/Makefile
docs/authors.rst
docs/conf.py
docs/contributing.rst
docs/history.rst
docs/index.rst
docs/installation.rst
docs/make.bat
docs/readme.rst
docs/usage.rst
qstatistic/__init__.py
qstatistic/qstatistic.py
qstatistic.egg-info/PKG-INFO
qstatistic.egg-info/SOURCES.txt
qstatistic.egg-info/dependency_links.txt
qstatistic.egg-info/not-zip-safe
qstatistic.egg-info/requires.txt
qstatistic.egg-info/top_level.txt
tests/__init__.py
tests/test_qstatistic.py