Metadata-Version: 1.1
Name: qstatistic
Version: 0.1.0.2
Summary: qstatistic Library.
Home-page: https://github.com/yan-duarte/qstatistic
Author: Yan Anderson Siriano Duarte
Author-email: yan_asd@hotmail.com
License: GNU General Public License v3
Keywords: qstatistic
Platform: UNKNOWN
Classifier: Development Status :: 2 - Pre-Alpha
Classifier: Intended Audience :: Developers
Classifier: License :: OSI Approved :: GNU General Public License v3 (GPLv3)
Classifier: Natural Language :: English
Classifier: Programming Language :: Python :: 3.6
